rgpd_pro_client/__init__.py
rgpd_pro_client/cli.py
rgpd_pro_client-2.0.7.dist-info/METADATA
rgpd_pro_client-2.0.7.dist-info/WHEEL
rgpd_pro_client-2.0.7.dist-info/entry_points.txt
rgpd_pro_client-2.0.7.dist-info/top_level.txt
rgpd_pro_client-2.0.7.dist-info/RECORD
