Metadata-Version: 2.4
Name: rgpd-pro-client
Version: 2.0.7
Summary: RGPD_PRO - Professional GDPR Compliance Scanner CLI Client
Home-page: https://github.com/yourusername/rgpd-pro-client
Author: Julien
Author-email: Julien <contact@rgpd-pro.com>
License: MIT
Project-URL: Homepage, https://github.com/yourusername/rgpd-pro-client
Project-URL: Documentation, https://github.com/yourusername/rgpd-pro-client/blob/main/README.md
Project-URL: Repository, https://github.com/yourusername/rgpd-pro-client
Project-URL: Issues, https://github.com/yourusername/rgpd-pro-client/issues
Keywords: gdpr,compliance,privacy,scanner,audit
Classifier: Development Status :: 4 - Beta
Classifier: Intended Audience :: Developers
Classifier: Intended Audience :: Legal Industry
Classifier: Topic :: Security
Classifier: Topic :: Software Development :: Testing
Classifier: License :: OSI Approved :: MIT License
Classifier: Programming Language :: Python :: 3
Classifier: Programming Language :: Python :: 3.8
Classifier: Programming Language :: Python :: 3.9
Classifier: Programming Language :: Python :: 3.10
Classifier: Programming Language :: Python :: 3.11
Classifier: Programming Language :: Python :: 3.12
Requires-Python: >=3.8
Requires-Dist: requests>=2.31.0
Dynamic: author
Dynamic: home-page
Dynamic: requires-python
